[
  {
    "name": "Please Touch Museum",
    "city": "Philadelphia",
    "state": "PA",
    "category": "Children's Museums",
    "subcategory": "Interactive Museum"
  },
  {
    "name": "Carnegie Museum of Natural History",
    "city": "Pittsburgh",
    "state": "PA",
    "category": "Children's Museums",
    "subcategory": "Natural History Museum"
  },
  {
    "name": "Pennsbury Manor",
    "city": "Morrisville",
    "state": "PA",
    "category": "Children's Museums",
    "subcategory": "Historic Site"
  },
  {
    "name": "The Rittenhouse Museum",
    "city": "Norriton",
    "state": "PA",
    "category": "Children's Museums",
    "subcategory": "Interactive Museum"
  },
  {
    "name": "Discovery Science Center",
    "city": "Harrisburg",
    "state": "PA",
    "category": "Science & Discovery Centers",
    "subcategory": "Science Center"
  },
  {
    "name": "Hershey's Chocolate World",
    "city": "Hershey",
    "state": "PA",
    "category": "Science & Discovery Centers",
    "subcategory": "Educational Center"
  },
  {
    "name": "Sky Zone Trampoline Park",
    "city": "Philadelphia",
    "state": "PA",
    "category": "Trampoline & Ninja Parks",
    "subcategory": "Trampoline Park"
  },
  {
    "name": "Urban Air Trampoline Park",
    "city": "Pittsburgh",
    "state": "PA",
    "category": "Trampoline & Ninja Parks",
    "subcategory": "Trampoline Park"
  },
  {
    "name": "Launch Trampoline Park",
    "city": "King of Prussia",
    "state": "PA",
    "category": "Trampoline & Ninja Parks",
    "subcategory": "Trampoline Park"
  },
  {
    "name": "Altitude Trampoline Park",
    "city": "Allentown",
    "state": "PA",
    "category": "Trampoline & Ninja Parks",
    "subcategory": "Trampoline Park"
  },
  {
    "name": "Ezone Indoor Playground",
    "city": "Philadelphia",
    "state": "PA",
    "category": "Indoor Playgrounds",
    "subcategory": "Indoor Play"
  },
  {
    "name": "Grand Central Station",
    "city": "Pittsburgh",
    "state": "PA",
    "category": "Indoor Playgrounds",
    "subcategory": "Indoor Play"
  },
  {
    "name": "Allegheny Gymnastics Academy",
    "city": "Pittsburgh",
    "state": "PA",
    "category": "Gymnastics Centers",
    "subcategory": "Gymnastics"
  },
  {
    "name": "Great Skate",
    "city": "Philadelphia",
    "state": "PA",
    "category": "Ice Skating Rinks",
    "subcategory": "Ice Skating"
  },
  {
    "name": "Clearview Ice Rinks",
    "city": "Hamburg",
    "state": "PA",
    "category": "Ice Skating Rinks",
    "subcategory": "Ice Skating"
  },
  {
    "name": "Skateland",
    "city": "Philadelphia",
    "state": "PA",
    "category": "Roller Skating Rinks",
    "subcategory": "Roller Skating"
  },
  {
    "name": "Skate Zone",
    "city": "Pittsburgh",
    "state": "PA",
    "category": "Roller Skating Rinks",
    "subcategory": "Roller Skating"
  },
  {
    "name": "AMF Bowling",
    "city": "Philadelphia",
    "state": "PA",
    "category": "Bowling Alleys",
    "subcategory": "Bowling"
  },
  {
    "name": "Bowlmor Lanes",
    "city": "Pittsburgh",
    "state": "PA",
    "category": "Bowling Alleys",
    "subcategory": "Bowling"
  },
  {
    "name": "Putt-Putt Golf & Games",
    "city": "Philadelphia",
    "state": "PA",
    "category": "Mini Golf & Batting Cages",
    "subcategory": "Mini Golf"
  },
  {
    "name": "Golf Quest",
    "city": "Pittsburgh",
    "state": "PA",
    "category": "Mini Golf & Batting Cages",
    "subcategory": "Mini Golf"
  },
  {
    "name": "Art Studio 4",
    "city": "Philadelphia",
    "state": "PA",
    "category": "Art Studios & Pottery",
    "subcategory": "Art Studio"
  },
  {
    "name": "Clay Fest",
    "city": "Pittsburgh",
    "state": "PA",
    "category": "Art Studios & Pottery",
    "subcategory": "Pottery Studio"
  },
  {
    "name": "Sandcastle Water Park",
    "city": "Pittsburgh",
    "state": "PA",
    "category": "Swimming & Splash Pads",
    "subcategory": "Water Park"
  },
  {
    "name": "Dorney Park & Wildwater Kingdom",
    "city": "Allentown",
    "state": "PA",
    "category": "Swimming & Splash Pads",
    "subcategory": "Water Park"
  },
  {
    "name": "Regal Cinemas",
    "city": "Philadelphia",
    "state": "PA",
    "category": "Movie Theaters",
    "subcategory": "Movie Theater"
  },
  {
    "name": "AMC Theaters",
    "city": "Pittsburgh",
    "state": "PA",
    "category": "Movie Theaters",
    "subcategory": "Movie Theater"
  },
  {
    "name": "Top Rope Climbing Gym",
    "city": "Philadelphia",
    "state": "PA",
    "category": "Climbing Gyms",
    "subcategory": "Climbing Gym"
  },
  {
    "name": "Pittsburgh Climbing Co.",
    "city": "Pittsburgh",
    "state": "PA",
    "category": "Climbing Gyms",
    "subcategory": "Climbing Gym"
  },
  {
    "name": "Dave & Buster's",
    "city": "Philadelphia",
    "state": "PA",
    "category": "Family Entertainment Centers",
    "subcategory": "Entertainment Center"
  },
  {
    "name": "Main Event",
    "city": "Pittsburgh",
    "state": "PA",
    "category": "Family Entertainment Centers",
    "subcategory": "Entertainment Center"
  },
  {
    "name": "Philadelphia Zoo",
    "city": "Philadelphia",
    "state": "PA",
    "category": "Farms, Zoos & Nature Centers",
    "subcategory": "Zoo"
  },
  {
    "name": "Phipps Conservatory",
    "city": "Pittsburgh",
    "state": "PA",
    "category": "Farms, Zoos & Nature Centers",
    "subcategory": "Nature Center"
  },
  {
    "name": "Elmwood Park Zoo",
    "city": "Norriton",
    "state": "PA",
    "category": "Farms, Zoos & Nature Centers",
    "subcategory": "Zoo"
  },
  {
    "name": "Liberty Science Center",
    "city": "Jersey City",
    "state": "NJ",
    "category": "Science & Discovery Centers",
    "subcategory": "Science Center"
  },
  {
    "name": "New Jersey Children's Museum",
    "city": "Paramus",
    "state": "NJ",
    "category": "Children's Museums",
    "subcategory": "Interactive Museum"
  },
  {
    "name": "Meadowlands Museum",
    "city": "Lyndhurst",
    "state": "NJ",
    "category": "Children's Museums",
    "subcategory": "Museum"
  },
  {
    "name": "Adventure Aquarium",
    "city": "Camden",
    "state": "NJ",
    "category": "Science & Discovery Centers",
    "subcategory": "Aquarium"
  },
  {
    "name": "Sky Zone Paramus",
    "city": "Paramus",
    "state": "NJ",
    "category": "Trampoline & Ninja Parks",
    "subcategory": "Trampoline Park"
  },
  {
    "name": "Urban Air North Bergen",
    "city": "North Bergen",
    "state": "NJ",
    "category": "Trampoline & Ninja Parks",
    "subcategory": "Trampoline Park"
  },
  {
    "name": "Altitude Trampoline Edison",
    "city": "Edison",
    "state": "NJ",
    "category": "Trampoline & Ninja Parks",
    "subcategory": "Trampoline Park"
  },
  {
    "name": "iPlay America",
    "city": "Bloomfield",
    "state": "NJ",
    "category": "Indoor Playgrounds",
    "subcategory": "Indoor Play"
  },
  {
    "name": "Grand Central Station",
    "city": "Paramus",
    "state": "NJ",
    "category": "Indoor Playgrounds",
    "subcategory": "Indoor Play"
  },
  {
    "name": "Elite Gymnastics Academy",
    "city": "New Jersey",
    "state": "NJ",
    "category": "Gymnastics Centers",
    "subcategory": "Gymnastics"
  },
  {
    "name": "Ice World Skating Rink",
    "city": "Paramus",
    "state": "NJ",
    "category": "Ice Skating Rinks",
    "subcategory": "Ice Skating"
  },
  {
    "name": "Ice Castle Arena",
    "city": "Hackensack",
    "state": "NJ",
    "category": "Ice Skating Rinks",
    "subcategory": "Ice Skating"
  },
  {
    "name": "Palisades Roller Skating Rink",
    "city": "Jersey City",
    "state": "NJ",
    "category": "Roller Skating Rinks",
    "subcategory": "Roller Skating"
  },
  {
    "name": "Bowlmor Lanes Princeton",
    "city": "Princeton",
    "state": "NJ",
    "category": "Bowling Alleys",
    "subcategory": "Bowling"
  },
  {
    "name": "AMF Bowling Paramus",
    "city": "Paramus",
    "state": "NJ",
    "category": "Bowling Alleys",
    "subcategory": "Bowling"
  },
  {
    "name": "Putt-Putt Golf",
    "city": "Paramus",
    "state": "NJ",
    "category": "Mini Golf & Batting Cages",
    "subcategory": "Mini Golf"
  },
  {
    "name": "Art Studio New Jersey",
    "city": "Princeton",
    "state": "NJ",
    "category": "Art Studios & Pottery",
    "subcategory": "Art Studio"
  },
  {
    "name": "Pottery Place Studio",
    "city": "Montclair",
    "state": "NJ",
    "category": "Art Studios & Pottery",
    "subcategory": "Pottery Studio"
  },
  {
    "name": "Hyper Hub Water Park",
    "city": "Secaucus",
    "state": "NJ",
    "category": "Swimming & Splash Pads",
    "subcategory": "Water Park"
  },
  {
    "name": "Regal Cinemas New Jersey",
    "city": "Paramus",
    "state": "NJ",
    "category": "Movie Theaters",
    "subcategory": "Movie Theater"
  },
  {
    "name": "AMC Theaters New Jersey",
    "city": "Jersey City",
    "state": "NJ",
    "category": "Movie Theaters",
    "subcategory": "Movie Theater"
  },
  {
    "name": "Climb NJ",
    "city": "East Rutherford",
    "state": "NJ",
    "category": "Climbing Gyms",
    "subcategory": "Climbing Gym"
  },
  {
    "name": "Quest Climbing Gym",
    "city": "Montclair",
    "state": "NJ",
    "category": "Climbing Gyms",
    "subcategory": "Climbing Gym"
  },
  {
    "name": "Dave & Buster's New Jersey",
    "city": "New Jersey",
    "state": "NJ",
    "category": "Family Entertainment Centers",
    "subcategory": "Entertainment Center"
  },
  {
    "name": "Main Event New Jersey",
    "city": "Paramus",
    "state": "NJ",
    "category": "Family Entertainment Centers",
    "subcategory": "Entertainment Center"
  },
  {
    "name": "Philadelphia Zoo Extension",
    "city": "Cherry Hill",
    "state": "NJ",
    "category": "Farms, Zoos & Nature Centers",
    "subcategory": "Zoo"
  },
  {
    "name": "Cohanzick Zoo",
    "city": "Bridgeton",
    "state": "NJ",
    "category": "Farms, Zoos & Nature Centers",
    "subcategory": "Zoo"
  },
  {
    "name": "Six Flags Great Adventure",
    "city": "Jackson",
    "state": "NJ",
    "category": "Farms, Zoos & Nature Centers",
    "subcategory": "Amusement Park"
  },
  {
    "name": "Delaware Children's Museum",
    "city": "Wilmington",
    "state": "DE",
    "category": "Children's Museums",
    "subcategory": "Interactive Museum"
  },
  {
    "name": "First State Heritage Park",
    "city": "Dover",
    "state": "DE",
    "category": "Children's Museums",
    "subcategory": "Historic Site"
  },
  {
    "name": "Delaware Science Center",
    "city": "Wilmington",
    "state": "DE",
    "category": "Science & Discovery Centers",
    "subcategory": "Science Center"
  },
  {
    "name": "Urban Air Wilmington",
    "city": "Wilmington",
    "state": "DE",
    "category": "Trampoline & Ninja Parks",
    "subcategory": "Trampoline Park"
  },
  {
    "name": "Altitude Trampoline Newark",
    "city": "Newark",
    "state": "DE",
    "category": "Trampoline & Ninja Parks",
    "subcategory": "Trampoline Park"
  },
  {
    "name": "Grand Central Station Wilmington",
    "city": "Wilmington",
    "state": "DE",
    "category": "Indoor Playgrounds",
    "subcategory": "Indoor Play"
  },
  {
    "name": "Gymnastics Plus",
    "city": "Wilmington",
    "state": "DE",
    "category": "Gymnastics Centers",
    "subcategory": "Gymnastics"
  },
  {
    "name": "Coral Street Arts Center",
    "city": "Wilmington",
    "state": "DE",
    "category": "Art Studios & Pottery",
    "subcategory": "Art Studio"
  },
  {
    "name": "Delaware Zoo",
    "city": "Wilmington",
    "state": "DE",
    "category": "Farms, Zoos & Nature Centers",
    "subcategory": "Zoo"
  },
  {
    "name": "Brandywine Zoo",
    "city": "Wilmington",
    "state": "DE",
    "category": "Farms, Zoos & Nature Centers",
    "subcategory": "Zoo"
  },
  {
    "name": "Delaware Rock Gym",
    "city": "Bear",
    "state": "DE",
    "category": "Climbing Gyms",
    "subcategory": "Rock Climbing"
  },
  {
    "name": "Patriot Ice Center",
    "city": "Newark",
    "state": "DE",
    "category": "Ice Skating Rinks",
    "subcategory": "Ice Rink"
  },
  {
    "name": "Bowlero New Castle",
    "city": "New Castle",
    "state": "DE",
    "category": "Bowling Alleys",
    "subcategory": "Bowling Alley"
  },
  {
    "name": "Shell We Bounce Trampoline Park",
    "city": "Lewes",
    "state": "DE",
    "category": "Trampoline & Ninja Parks",
    "subcategory": "Trampoline Park"
  },
  {
    "name": "Vince's Sports Center",
    "city": "Newark",
    "state": "DE",
    "category": "Mini Golf & Batting Cages",
    "subcategory": "Mini Golf"
  },
  {
    "name": "Cape Henlopen State Park",
    "city": "Lewes",
    "state": "DE",
    "category": "Farms, Zoos & Nature Centers",
    "subcategory": "State Park"
  },
  {
    "name": "Bronx Zoo",
    "city": "Bronx",
    "state": "NY",
    "category": "Farms, Zoos & Nature Centers",
    "subcategory": "Zoo"
  },
  {
    "name": "Central Park Zoo",
    "city": "New York",
    "state": "NY",
    "category": "Farms, Zoos & Nature Centers",
    "subcategory": "Zoo"
  },
  {
    "name": "Shedd Aquarium",
    "city": "New York",
    "state": "NY",
    "category": "Science & Discovery Centers",
    "subcategory": "Aquarium"
  },
  {
    "name": "Museum of Mathematics",
    "city": "New York",
    "state": "NY",
    "category": "Science & Discovery Centers",
    "subcategory": "Science Museum"
  },
  {
    "name": "American Museum of Natural History",
    "city": "New York",
    "state": "NY",
    "category": "Children's Museums",
    "subcategory": "Natural History Museum"
  },
  {
    "name": "Children's Museum of Manhattan",
    "city": "New York",
    "state": "NY",
    "category": "Children's Museums",
    "subcategory": "Interactive Museum"
  },
  {
    "name": "Intrepid Sea, Air & Space Museum",
    "city": "New York",
    "state": "NY",
    "category": "Children's Museums",
    "subcategory": "Museum"
  },
  {
    "name": "New York Hall of Science",
    "city": "Flushing",
    "state": "NY",
    "category": "Science & Discovery Centers",
    "subcategory": "Science Center"
  },
  {
    "name": "Sky Zone Manhattan",
    "city": "New York",
    "state": "NY",
    "category": "Trampoline & Ninja Parks",
    "subcategory": "Trampoline Park"
  },
  {
    "name": "Urban Air Queens",
    "city": "Queens",
    "state": "NY",
    "category": "Trampoline & Ninja Parks",
    "subcategory": "Trampoline Park"
  },
  {
    "name": "Altitude Trampoline Brooklyn",
    "city": "Brooklyn",
    "state": "NY",
    "category": "Trampoline & Ninja Parks",
    "subcategory": "Trampoline Park"
  },
  {
    "name": "Grand Central Terminal Play",
    "city": "New York",
    "state": "NY",
    "category": "Indoor Playgrounds",
    "subcategory": "Indoor Play"
  },
  {
    "name": "Manhattan Gymnastics Academy",
    "city": "New York",
    "state": "NY",
    "category": "Gymnastics Centers",
    "subcategory": "Gymnastics"
  },
  {
    "name": "Sky Rink",
    "city": "New York",
    "state": "NY",
    "category": "Ice Skating Rinks",
    "subcategory": "Ice Skating"
  },
  {
    "name": "Rockefeller Center Ice Rink",
    "city": "New York",
    "state": "NY",
    "category": "Ice Skating Rinks",
    "subcategory": "Ice Skating"
  },
  {
    "name": "Roller Skating New York",
    "city": "New York",
    "state": "NY",
    "category": "Roller Skating Rinks",
    "subcategory": "Roller Skating"
  },
  {
    "name": "AMF Bowling New York",
    "city": "New York",
    "state": "NY",
    "category": "Bowling Alleys",
    "subcategory": "Bowling"
  },
  {
    "name": "Bowlmor Lanes New York",
    "city": "New York",
    "state": "NY",
    "category": "Bowling Alleys",
    "subcategory": "Bowling"
  },
  {
    "name": "Mini Golf New York",
    "city": "New York",
    "state": "NY",
    "category": "Mini Golf & Batting Cages",
    "subcategory": "Mini Golf"
  },
  {
    "name": "Art Studio New York",
    "city": "New York",
    "state": "NY",
    "category": "Art Studios & Pottery",
    "subcategory": "Art Studio"
  },
  {
    "name": "Pottery Studio Manhattan",
    "city": "New York",
    "state": "NY",
    "category": "Art Studios & Pottery",
    "subcategory": "Pottery Studio"
  },
  {
    "name": "Splash Pad New York",
    "city": "New York",
    "state": "NY",
    "category": "Swimming & Splash Pads",
    "subcategory": "Water Park"
  },
  {
    "name": "AMC Theaters New York",
    "city": "New York",
    "state": "NY",
    "category": "Movie Theaters",
    "subcategory": "Movie Theater"
  },
  {
    "name": "Regal Cinemas New York",
    "city": "New York",
    "state": "NY",
    "category": "Movie Theaters",
    "subcategory": "Movie Theater"
  },
  {
    "name": "Cliff Climbing Gym",
    "city": "New York",
    "state": "NY",
    "category": "Climbing Gyms",
    "subcategory": "Climbing Gym"
  },
  {
    "name": "Quest Climbing New York",
    "city": "Brooklyn",
    "state": "NY",
    "category": "Climbing Gyms",
    "subcategory": "Climbing Gym"
  },
  {
    "name": "Dave & Buster's New York",
    "city": "New York",
    "state": "NY",
    "category": "Family Entertainment Centers",
    "subcategory": "Entertainment Center"
  },
  {
    "name": "Main Event New York",
    "city": "Queens",
    "state": "NY",
    "category": "Family Entertainment Centers",
    "subcategory": "Entertainment Center"
  },
  {
    "name": "Boston Children's Museum",
    "city": "Boston",
    "state": "MA",
    "category": "Children's Museums",
    "subcategory": "Interactive Museum"
  },
  {
    "name": "Museum of Science",
    "city": "Boston",
    "state": "MA",
    "category": "Science & Discovery Centers",
    "subcategory": "Science Center"
  },
  {
    "name": "Franklin Park Zoo",
    "city": "Boston",
    "state": "MA",
    "category": "Farms, Zoos & Nature Centers",
    "subcategory": "Zoo"
  },
  {
    "name": "New England Aquarium",
    "city": "Boston",
    "state": "MA",
    "category": "Science & Discovery Centers",
    "subcategory": "Aquarium"
  },
  {
    "name": "Isabella Stewart Gardner Museum",
    "city": "Boston",
    "state": "MA",
    "category": "Children's Museums",
    "subcategory": "Art Museum"
  },
  {
    "name": "Sky Zone Boston",
    "city": "Boston",
    "state": "MA",
    "category": "Trampoline & Ninja Parks",
    "subcategory": "Trampoline Park"
  },
  {
    "name": "Urban Air Boston",
    "city": "Boston",
    "state": "MA",
    "category": "Trampoline & Ninja Parks",
    "subcategory": "Trampoline Park"
  },
  {
    "name": "Altitude Trampoline Worcester",
    "city": "Worcester",
    "state": "MA",
    "category": "Trampoline & Ninja Parks",
    "subcategory": "Trampoline Park"
  },
  {
    "name": "Grand Central Station Boston",
    "city": "Boston",
    "state": "MA",
    "category": "Indoor Playgrounds",
    "subcategory": "Indoor Play"
  },
  {
    "name": "Boston Gymnastics Academy",
    "city": "Boston",
    "state": "MA",
    "category": "Gymnastics Centers",
    "subcategory": "Gymnastics"
  },
  {
    "name": "Skating Club of Boston",
    "city": "Boston",
    "state": "MA",
    "category": "Ice Skating Rinks",
    "subcategory": "Ice Skating"
  },
  {
    "name": "Roller Skating Boston",
    "city": "Boston",
    "state": "MA",
    "category": "Roller Skating Rinks",
    "subcategory": "Roller Skating"
  },
  {
    "name": "AMF Bowling Boston",
    "city": "Boston",
    "state": "MA",
    "category": "Bowling Alleys",
    "subcategory": "Bowling"
  },
  {
    "name": "Bowlmor Lanes Boston",
    "city": "Boston",
    "state": "MA",
    "category": "Bowling Alleys",
    "subcategory": "Bowling"
  },
  {
    "name": "Mini Golf Boston",
    "city": "Boston",
    "state": "MA",
    "category": "Mini Golf & Batting Cages",
    "subcategory": "Mini Golf"
  },
  {
    "name": "Art Studio Boston",
    "city": "Boston",
    "state": "MA",
    "category": "Art Studios & Pottery",
    "subcategory": "Art Studio"
  },
  {
    "name": "Pottery Place Boston",
    "city": "Boston",
    "state": "MA",
    "category": "Art Studios & Pottery",
    "subcategory": "Pottery Studio"
  },
  {
    "name": "Water Park Boston",
    "city": "Boston",
    "state": "MA",
    "category": "Swimming & Splash Pads",
    "subcategory": "Water Park"
  },
  {
    "name": "AMC Theaters Boston",
    "city": "Boston",
    "state": "MA",
    "category": "Movie Theaters",
    "subcategory": "Movie Theater"
  },
  {
    "name": "Regal Cinemas Boston",
    "city": "Boston",
    "state": "MA",
    "category": "Movie Theaters",
    "subcategory": "Movie Theater"
  },
  {
    "name": "Boston Climbing Gym",
    "city": "Boston",
    "state": "MA",
    "category": "Climbing Gyms",
    "subcategory": "Climbing Gym"
  },
  {
    "name": "Quest Climbing Boston",
    "city": "Boston",
    "state": "MA",
    "category": "Climbing Gyms",
    "subcategory": "Climbing Gym"
  },
  {
    "name": "Dave & Buster's Boston",
    "city": "Boston",
    "state": "MA",
    "category": "Family Entertainment Centers",
    "subcategory": "Entertainment Center"
  },
  {
    "name": "Main Event Boston",
    "city": "Boston",
    "state": "MA",
    "category": "Family Entertainment Centers",
    "subcategory": "Entertainment Center"
  },
  {
    "name": "Southwick's Zoo",
    "city": "Mendon",
    "state": "MA",
    "category": "Farms, Zoos & Nature Centers",
    "subcategory": "Zoo"
  },
  {
    "name": "Providence Children's Museum",
    "city": "Providence",
    "state": "RI",
    "category": "Children's Museums",
    "subcategory": "Interactive Museum"
  },
  {
    "name": "Roger Williams Zoo",
    "city": "Bristol",
    "state": "RI",
    "category": "Farms, Zoos & Nature Centers",
    "subcategory": "Zoo"
  },
  {
    "name": "Sky Zone Providence",
    "city": "Providence",
    "state": "RI",
    "category": "Trampoline & Ninja Parks",
    "subcategory": "Trampoline Park"
  },
  {
    "name": "Urban Air Warwick",
    "city": "Warwick",
    "state": "RI",
    "category": "Trampoline & Ninja Parks",
    "subcategory": "Trampoline Park"
  },
  {
    "name": "Grand Central Station Providence",
    "city": "Providence",
    "state": "RI",
    "category": "Indoor Playgrounds",
    "subcategory": "Indoor Play"
  },
  {
    "name": "Providence Rock Gym",
    "city": "Providence",
    "state": "RI",
    "category": "Climbing Gyms",
    "subcategory": "Rock Climbing"
  },
  {
    "name": "Bowl New England Providence",
    "city": "Providence",
    "state": "RI",
    "category": "Bowling Alleys",
    "subcategory": "Bowling Alley"
  },
  {
    "name": "Skating Club of Rhode Island",
    "city": "Pawtucket",
    "state": "RI",
    "category": "Ice Skating Rinks",
    "subcategory": "Ice Rink"
  },
  {
    "name": "Skating Club of Providence",
    "city": "Providence",
    "state": "RI",
    "category": "Ice Skating Rinks",
    "subcategory": "Ice Rink"
  },
  {
    "name": "Newport Polo",
    "city": "Portsmouth",
    "state": "RI",
    "category": "Farms, Zoos & Nature Centers",
    "subcategory": "Farm"
  },
  {
    "name": "Bowlero Providence",
    "city": "Providence",
    "state": "RI",
    "category": "Bowling Alleys",
    "subcategory": "Bowling Alley"
  },
  {
    "name": "Quonset Davisville Ice Rink",
    "city": "North Kingstown",
    "state": "RI",
    "category": "Ice Skating Rinks",
    "subcategory": "Ice Rink"
  },
  {
    "name": "WaterFire Arts Center",
    "city": "Providence",
    "state": "RI",
    "category": "Art Studios & Pottery",
    "subcategory": "Art Studio"
  },
  {
    "name": "Climbing Lab Providence",
    "city": "Providence",
    "state": "RI",
    "category": "Climbing Gyms",
    "subcategory": "Rock Climbing"
  },
  {
    "name": "Dave and Buster's Providence",
    "city": "Providence",
    "state": "RI",
    "category": "Family Entertainment Centers",
    "subcategory": "FEC"
  },
  {
    "name": "Connecticut Science Center",
    "city": "Hartford",
    "state": "CT",
    "category": "Science & Discovery Centers",
    "subcategory": "Science Center"
  },
  {
    "name": "Yale Peabody Museum",
    "city": "New Haven",
    "state": "CT",
    "category": "Children's Museums",
    "subcategory": "Natural History Museum"
  },
  {
    "name": "Beardsley Zoo",
    "city": "Bridgeport",
    "state": "CT",
    "category": "Farms, Zoos & Nature Centers",
    "subcategory": "Zoo"
  },
  {
    "name": "Sky Zone Hartford",
    "city": "Hartford",
    "state": "CT",
    "category": "Trampoline & Ninja Parks",
    "subcategory": "Trampoline Park"
  },
  {
    "name": "Urban Air New Haven",
    "city": "New Haven",
    "state": "CT",
    "category": "Trampoline & Ninja Parks",
    "subcategory": "Trampoline Park"
  },
  {
    "name": "Grand Central Station Hartford",
    "city": "Hartford",
    "state": "CT",
    "category": "Indoor Playgrounds",
    "subcategory": "Indoor Play"
  },
  {
    "name": "The Maritime Aquarium at Norwalk",
    "city": "Norwalk",
    "state": "CT",
    "category": "Science & Discovery Centers",
    "subcategory": "Aquarium"
  },
  {
    "name": "Stepping Stones Museum for Children",
    "city": "Norwalk",
    "state": "CT",
    "category": "Children's Museums",
    "subcategory": "Children's Museum"
  },
  {
    "name": "Sports Center of Connecticut",
    "city": "Shelton",
    "state": "CT",
    "category": "Ice Skating Rinks",
    "subcategory": "Ice Rink"
  },
  {
    "name": "Bowlero Milford",
    "city": "Milford",
    "state": "CT",
    "category": "Bowling Alleys",
    "subcategory": "Bowling Alley"
  },
  {
    "name": "Sky Zone Wallingford",
    "city": "Wallingford",
    "state": "CT",
    "category": "Trampoline & Ninja Parks",
    "subcategory": "Trampoline Park"
  },
  {
    "name": "New Milford Trampoline Park",
    "city": "New Milford",
    "state": "CT",
    "category": "Trampoline & Ninja Parks",
    "subcategory": "Trampoline Park"
  },
  {
    "name": "Chelsea Piers Connecticut",
    "city": "Stamford",
    "state": "CT",
    "category": "Gymnastics Centers",
    "subcategory": "Gymnastics"
  },
  {
    "name": "Wonderland of Ice",
    "city": "Bridgeport",
    "state": "CT",
    "category": "Ice Skating Rinks",
    "subcategory": "Ice Rink"
  },
  {
    "name": "Mystic Seaport Museum",
    "city": "Mystic",
    "state": "CT",
    "category": "Science & Discovery Centers",
    "subcategory": "Museum"
  },
  {
    "name": "Children's Museum of NH",
    "city": "Dover",
    "state": "NH",
    "category": "Children's Museums",
    "subcategory": "Interactive Museum"
  },
  {
    "name": "Squam Lakes Natural Science Center",
    "city": "Holderness",
    "state": "NH",
    "category": "Farms, Zoos & Nature Centers",
    "subcategory": "Nature Center"
  },
  {
    "name": "Sky Zone Manchester",
    "city": "Manchester",
    "state": "NH",
    "category": "Trampoline & Ninja Parks",
    "subcategory": "Trampoline Park"
  },
  {
    "name": "Urban Air Nashua",
    "city": "Nashua",
    "state": "NH",
    "category": "Trampoline & Ninja Parks",
    "subcategory": "Trampoline Park"
  },
  {
    "name": "Children's Museum & Theatre of Maine",
    "city": "Portland",
    "state": "ME",
    "category": "Children's Museums",
    "subcategory": "Interactive Museum"
  },
  {
    "name": "Maine Wildlife Park",
    "city": "Gray",
    "state": "ME",
    "category": "Farms, Zoos & Nature Centers",
    "subcategory": "Wildlife Park"
  },
  {
    "name": "Sky Zone Portland",
    "city": "Portland",
    "state": "ME",
    "category": "Trampoline & Ninja Parks",
    "subcategory": "Trampoline Park"
  },
  {
    "name": "Marbles Kids Museum",
    "city": "Raleigh",
    "state": "NC",
    "category": "Children's Museums",
    "subcategory": "Interactive Museum"
  },
  {
    "name": "Discovery Place",
    "city": "Charlotte",
    "state": "NC",
    "category": "Science & Discovery Centers",
    "subcategory": "Science Center"
  },
  {
    "name": "North Carolina Zoo",
    "city": "Asheboro",
    "state": "NC",
    "category": "Farms, Zoos & Nature Centers",
    "subcategory": "Zoo"
  },
  {
    "name": "Sky Zone Raleigh",
    "city": "Raleigh",
    "state": "NC",
    "category": "Trampoline & Ninja Parks",
    "subcategory": "Trampoline Park"
  },
  {
    "name": "Urban Air Charlotte",
    "city": "Charlotte",
    "state": "NC",
    "category": "Trampoline & Ninja Parks",
    "subcategory": "Trampoline Park"
  },
  {
    "name": "Altitude Trampoline Greensboro",
    "city": "Greensboro",
    "state": "NC",
    "category": "Trampoline & Ninja Parks",
    "subcategory": "Trampoline Park"
  },
  {
    "name": "Grand Central Station Raleigh",
    "city": "Raleigh",
    "state": "NC",
    "category": "Indoor Playgrounds",
    "subcategory": "Indoor Play"
  },
  {
    "name": "Polar Ice Raleigh",
    "city": "Raleigh",
    "state": "NC",
    "category": "Ice Skating Rinks",
    "subcategory": "Ice Skating"
  },
  {
    "name": "Triangle Rock Club",
    "city": "Raleigh",
    "state": "NC",
    "category": "Climbing Gyms",
    "subcategory": "Climbing Gym"
  },
  {
    "name": "Inner Peaks Climbing",
    "city": "Charlotte",
    "state": "NC",
    "category": "Climbing Gyms",
    "subcategory": "Climbing Gym"
  },
  {
    "name": "Bowlero Raleigh",
    "city": "Raleigh",
    "state": "NC",
    "category": "Bowling Alleys",
    "subcategory": "Bowling"
  },
  {
    "name": "Bowlero Charlotte",
    "city": "Charlotte",
    "state": "NC",
    "category": "Bowling Alleys",
    "subcategory": "Bowling"
  },
  {
    "name": "Alamo Drafthouse Raleigh",
    "city": "Raleigh",
    "state": "NC",
    "category": "Movie Theaters",
    "subcategory": "Movie Theater"
  },
  {
    "name": "AMC Carolina Pavilion 22",
    "city": "Charlotte",
    "state": "NC",
    "category": "Movie Theaters",
    "subcategory": "Movie Theater"
  },
  {
    "name": "Raleigh School of Gymnastics",
    "city": "Raleigh",
    "state": "NC",
    "category": "Gymnastics Centers",
    "subcategory": "Gymnastics"
  },
  {
    "name": "Ray's Splash Planet",
    "city": "Charlotte",
    "state": "NC",
    "category": "Swimming & Splash Pads",
    "subcategory": "Splash Pad"
  },
  {
    "name": "Swingin' Things",
    "city": "Jacksonville",
    "state": "NC",
    "category": "Mini Golf & Batting Cages",
    "subcategory": "Mini Golf"
  },
  {
    "name": "Painting with a Twist Charlotte",
    "city": "Charlotte",
    "state": "NC",
    "category": "Art Studios & Pottery",
    "subcategory": "Art Studio"
  },
  {
    "name": "EdVenture Children's Museum",
    "city": "Columbia",
    "state": "SC",
    "category": "Children's Museums",
    "subcategory": "Interactive Museum"
  },
  {
    "name": "Riverbanks Zoo",
    "city": "Columbia",
    "state": "SC",
    "category": "Farms, Zoos & Nature Centers",
    "subcategory": "Zoo"
  },
  {
    "name": "Sky Zone Columbia",
    "city": "Columbia",
    "state": "SC",
    "category": "Trampoline & Ninja Parks",
    "subcategory": "Trampoline Park"
  },
  {
    "name": "Urban Air Greenville",
    "city": "Greenville",
    "state": "SC",
    "category": "Trampoline & Ninja Parks",
    "subcategory": "Trampoline Park"
  },
  {
    "name": "Grand Central Station Charleston",
    "city": "Charleston",
    "state": "SC",
    "category": "Indoor Playgrounds",
    "subcategory": "Indoor Play"
  },
  {
    "name": "Carolina Ice Palace",
    "city": "North Charleston",
    "state": "SC",
    "category": "Ice Skating Rinks",
    "subcategory": "Ice Skating"
  },
  {
    "name": "Bowlero Greenville",
    "city": "Greenville",
    "state": "SC",
    "category": "Bowling Alleys",
    "subcategory": "Bowling"
  },
  {
    "name": "FlipCity South",
    "city": "Columbia",
    "state": "SC",
    "category": "Gymnastics Centers",
    "subcategory": "Gymnastics"
  },
  {
    "name": "Splash Island Waterpark",
    "city": "Mount Pleasant",
    "state": "SC",
    "category": "Swimming & Splash Pads",
    "subcategory": "Water Park"
  },
  {
    "name": "Frankie's Fun Park",
    "city": "Greenville",
    "state": "SC",
    "category": "Mini Golf & Batting Cages",
    "subcategory": "Mini Golf"
  },
  {
    "name": "WonderWorks Myrtle Beach",
    "city": "Myrtle Beach",
    "state": "SC",
    "category": "Science & Discovery Centers",
    "subcategory": "Science Museum"
  },
  {
    "name": "Broadway Grand Prix Myrtle Beach",
    "city": "Myrtle Beach",
    "state": "SC",
    "category": "Mini Golf & Batting Cages",
    "subcategory": "Mini Golf"
  },
  {
    "name": "Bowlero Columbia",
    "city": "Columbia",
    "state": "SC",
    "category": "Bowling Alleys",
    "subcategory": "Bowling Alley"
  },
  {
    "name": "Sky Zone Charleston",
    "city": "Charleston",
    "state": "SC",
    "category": "Trampoline & Ninja Parks",
    "subcategory": "Trampoline Park"
  },
  {
    "name": "Riverbanks Zoo Botanical Garden",
    "city": "Columbia",
    "state": "SC",
    "category": "Farms, Zoos & Nature Centers",
    "subcategory": "Botanical Garden"
  },
  {
    "name": "Charleston Museum",
    "city": "Charleston",
    "state": "SC",
    "category": "Science & Discovery Centers",
    "subcategory": "Museum"
  },
  {
    "name": "Children's Museum of Atlanta",
    "city": "Atlanta",
    "state": "GA",
    "category": "Children's Museums",
    "subcategory": "Interactive Museum"
  },
  {
    "name": "Zoo Atlanta",
    "city": "Atlanta",
    "state": "GA",
    "category": "Farms, Zoos & Nature Centers",
    "subcategory": "Zoo"
  },
  {
    "name": "Georgia Aquarium",
    "city": "Atlanta",
    "state": "GA",
    "category": "Science & Discovery Centers",
    "subcategory": "Aquarium"
  },
  {
    "name": "Sky Zone Atlanta",
    "city": "Atlanta",
    "state": "GA",
    "category": "Trampoline & Ninja Parks",
    "subcategory": "Trampoline Park"
  },
  {
    "name": "Urban Air Savannah",
    "city": "Savannah",
    "state": "GA",
    "category": "Trampoline & Ninja Parks",
    "subcategory": "Trampoline Park"
  },
  {
    "name": "Altitude Trampoline Augusta",
    "city": "Augusta",
    "state": "GA",
    "category": "Trampoline & Ninja Parks",
    "subcategory": "Trampoline Park"
  },
  {
    "name": "Grand Central Station Atlanta",
    "city": "Atlanta",
    "state": "GA",
    "category": "Indoor Playgrounds",
    "subcategory": "Indoor Play"
  },
  {
    "name": "Georgia Gymnastics Academy",
    "city": "Alpharetta",
    "state": "GA",
    "category": "Gymnastics Centers",
    "subcategory": "Gymnastics"
  },
  {
    "name": "Putt Putt Fun Center Augusta",
    "city": "Augusta",
    "state": "GA",
    "category": "Mini Golf & Batting Cages",
    "subcategory": "Mini Golf"
  },
  {
    "name": "Color Me Mine Atlanta",
    "city": "Atlanta",
    "state": "GA",
    "category": "Art Studios & Pottery",
    "subcategory": "Art Studio"
  },
  {
    "name": "Coca-Cola Space Science Center",
    "city": "Columbus",
    "state": "GA",
    "category": "Science & Discovery Centers",
    "subcategory": "Science Museum"
  },
  {
    "name": "Museum of Arts and Sciences Macon",
    "city": "Macon",
    "state": "GA",
    "category": "Science & Discovery Centers",
    "subcategory": "Science Museum"
  },
  {
    "name": "Stone Summit Climbing Atlanta",
    "city": "Atlanta",
    "state": "GA",
    "category": "Climbing Gyms",
    "subcategory": "Rock Climbing"
  },
  {
    "name": "Bowlero Atlanta",
    "city": "Atlanta",
    "state": "GA",
    "category": "Bowling Alleys",
    "subcategory": "Bowling Alley"
  },
  {
    "name": "Ice Forum at Peachtree City",
    "city": "Peachtree City",
    "state": "GA",
    "category": "Ice Skating Rinks",
    "subcategory": "Ice Rink"
  },
  {
    "name": "National Infantry Museum",
    "city": "Columbus",
    "state": "GA",
    "category": "Science & Discovery Centers",
    "subcategory": "Museum"
  },
  {
    "name": "Miami Children's Museum",
    "city": "Miami",
    "state": "FL",
    "category": "Children's Museums",
    "subcategory": "Interactive Museum"
  },
  {
    "name": "Orlando Science Center",
    "city": "Orlando",
    "state": "FL",
    "category": "Science & Discovery Centers",
    "subcategory": "Science Center"
  },
  {
    "name": "ZooTampa",
    "city": "Tampa",
    "state": "FL",
    "category": "Farms, Zoos & Nature Centers",
    "subcategory": "Zoo"
  },
  {
    "name": "Miami Seaquarium",
    "city": "Miami",
    "state": "FL",
    "category": "Science & Discovery Centers",
    "subcategory": "Aquarium"
  },
  {
    "name": "Sky Zone Miami",
    "city": "Miami",
    "state": "FL",
    "category": "Trampoline & Ninja Parks",
    "subcategory": "Trampoline Park"
  },
  {
    "name": "Urban Air Tampa",
    "city": "Tampa",
    "state": "FL",
    "category": "Trampoline & Ninja Parks",
    "subcategory": "Trampoline Park"
  },
  {
    "name": "Altitude Trampoline Orlando",
    "city": "Orlando",
    "state": "FL",
    "category": "Trampoline & Ninja Parks",
    "subcategory": "Trampoline Park"
  },
  {
    "name": "Grand Central Station Miami",
    "city": "Miami",
    "state": "FL",
    "category": "Indoor Playgrounds",
    "subcategory": "Indoor Play"
  },
  {
    "name": "Glazer Children's Museum",
    "city": "Tampa",
    "state": "FL",
    "category": "Children's Museums",
    "subcategory": "Children's Museum"
  },
  {
    "name": "Crayola Experience Orlando",
    "city": "Orlando",
    "state": "FL",
    "category": "Children's Museums",
    "subcategory": "Children's Museum"
  },
  {
    "name": "Discovery Science Center Broward",
    "city": "Fort Lauderdale",
    "state": "FL",
    "category": "Science & Discovery Centers",
    "subcategory": "Science Museum"
  },
  {
    "name": "Sky Zone Jacksonville",
    "city": "Jacksonville",
    "state": "FL",
    "category": "Trampoline & Ninja Parks",
    "subcategory": "Trampoline Park"
  },
  {
    "name": "Urban Air Jacksonville",
    "city": "Jacksonville",
    "state": "FL",
    "category": "Trampoline & Ninja Parks",
    "subcategory": "Trampoline Park"
  },
  {
    "name": "Sky Zone Fort Lauderdale",
    "city": "Fort Lauderdale",
    "state": "FL",
    "category": "Trampoline & Ninja Parks",
    "subcategory": "Trampoline Park"
  },
  {
    "name": "Iceland of Pinellas",
    "city": "Clearwater",
    "state": "FL",
    "category": "Ice Skating Rinks",
    "subcategory": "Ice Rink"
  },
  {
    "name": "Bowlero Fort Lauderdale",
    "city": "Fort Lauderdale",
    "state": "FL",
    "category": "Bowling Alleys",
    "subcategory": "Bowling Alley"
  },
  {
    "name": "AMC Town Center 20 Jacksonville",
    "city": "Jacksonville",
    "state": "FL",
    "category": "Movie Theaters",
    "subcategory": "Movie Theater"
  },
  {
    "name": "Morikami Museum and Japanese Gardens",
    "city": "Delray Beach",
    "state": "FL",
    "category": "Farms, Zoos & Nature Centers",
    "subcategory": "Museum"
  },
  {
    "name": "McWane Science Center",
    "city": "Birmingham",
    "state": "AL",
    "category": "Science & Discovery Centers",
    "subcategory": "Science Center"
  },
  {
    "name": "Birmingham Zoo",
    "city": "Birmingham",
    "state": "AL",
    "category": "Farms, Zoos & Nature Centers",
    "subcategory": "Zoo"
  },
  {
    "name": "Sky Zone Birmingham",
    "city": "Birmingham",
    "state": "AL",
    "category": "Trampoline & Ninja Parks",
    "subcategory": "Trampoline Park"
  },
  {
    "name": "Urban Air Montgomery",
    "city": "Montgomery",
    "state": "AL",
    "category": "Trampoline & Ninja Parks",
    "subcategory": "Trampoline Park"
  },
  {
    "name": "Grand Central Station Birmingham",
    "city": "Birmingham",
    "state": "AL",
    "category": "Indoor Playgrounds",
    "subcategory": "Indoor Play"
  },
  {
    "name": "High Point Climbing",
    "city": "Birmingham",
    "state": "AL",
    "category": "Climbing Gyms",
    "subcategory": "Climbing Gym"
  },
  {
    "name": "Alabama Splash Adventure",
    "city": "Bessemer",
    "state": "AL",
    "category": "Swimming & Splash Pads",
    "subcategory": "Water Park"
  },
  {
    "name": "U.S. Space & Rocket Center",
    "city": "Huntsville",
    "state": "AL",
    "category": "Science & Discovery Centers",
    "subcategory": "Science Museum"
  },
  {
    "name": "Gulf Coast Exploreum",
    "city": "Mobile",
    "state": "AL",
    "category": "Science & Discovery Centers",
    "subcategory": "Science Museum"
  },
  {
    "name": "Sky Zone Huntsville",
    "city": "Huntsville",
    "state": "AL",
    "category": "Trampoline & Ninja Parks",
    "subcategory": "Trampoline Park"
  },
  {
    "name": "Mobile Zoo",
    "city": "Theodore",
    "state": "AL",
    "category": "Farms, Zoos & Nature Centers",
    "subcategory": "Zoo"
  },
  {
    "name": "Bowlero Huntsville",
    "city": "Huntsville",
    "state": "AL",
    "category": "Bowling Alleys",
    "subcategory": "Bowling Alley"
  },
  {
    "name": "Adventure Science Center",
    "city": "Nashville",
    "state": "TN",
    "category": "Science & Discovery Centers",
    "subcategory": "Science Center"
  },
  {
    "name": "Nashville Zoo",
    "city": "Nashville",
    "state": "TN",
    "category": "Farms, Zoos & Nature Centers",
    "subcategory": "Zoo"
  },
  {
    "name": "Sky Zone Nashville",
    "city": "Nashville",
    "state": "TN",
    "category": "Trampoline & Ninja Parks",
    "subcategory": "Trampoline Park"
  },
  {
    "name": "Urban Air Memphis",
    "city": "Memphis",
    "state": "TN",
    "category": "Trampoline & Ninja Parks",
    "subcategory": "Trampoline Park"
  },
  {
    "name": "Grand Central Station Nashville",
    "city": "Nashville",
    "state": "TN",
    "category": "Indoor Playgrounds",
    "subcategory": "Indoor Play"
  },
  {
    "name": "Centennial Sportsplex",
    "city": "Nashville",
    "state": "TN",
    "category": "Ice Skating Rinks",
    "subcategory": "Ice Skating"
  },
  {
    "name": "Ford Ice Center",
    "city": "Antioch",
    "state": "TN",
    "category": "Ice Skating Rinks",
    "subcategory": "Ice Skating"
  },
  {
    "name": "Climb Nashville",
    "city": "Nashville",
    "state": "TN",
    "category": "Climbing Gyms",
    "subcategory": "Climbing Gym"
  },
  {
    "name": "Bowlero Bartlett",
    "city": "Bartlett",
    "state": "TN",
    "category": "Bowling Alleys",
    "subcategory": "Bowling"
  },
  {
    "name": "Nashville Gymnastics Training Center",
    "city": "Nashville",
    "state": "TN",
    "category": "Gymnastics Centers",
    "subcategory": "Gymnastics"
  },
  {
    "name": "Nashville Shores Waterpark",
    "city": "Nashville",
    "state": "TN",
    "category": "Swimming & Splash Pads",
    "subcategory": "Water Park"
  },
  {
    "name": "Dollywood's Splash Country",
    "city": "Pigeon Forge",
    "state": "TN",
    "category": "Swimming & Splash Pads",
    "subcategory": "Water Park"
  },
  {
    "name": "Farragut Golf and Games",
    "city": "Knoxville",
    "state": "TN",
    "category": "Mini Golf & Batting Cages",
    "subcategory": "Mini Golf"
  },
  {
    "name": "Painting with a Twist Nashville",
    "city": "Nashville",
    "state": "TN",
    "category": "Art Studios & Pottery",
    "subcategory": "Art Studio"
  },
  {
    "name": "Mississippi Children's Museum",
    "city": "Jackson",
    "state": "MS",
    "category": "Children's Museums",
    "subcategory": "Interactive Museum"
  },
  {
    "name": "Mississippi Zoo",
    "city": "Pearl",
    "state": "MS",
    "category": "Farms, Zoos & Nature Centers",
    "subcategory": "Zoo"
  },
  {
    "name": "Sky Zone Jackson",
    "city": "Jackson",
    "state": "MS",
    "category": "Trampoline & Ninja Parks",
    "subcategory": "Trampoline Park"
  },
  {
    "name": "Urban Air Gulfport",
    "city": "Gulfport",
    "state": "MS",
    "category": "Trampoline & Ninja Parks",
    "subcategory": "Trampoline Park"
  },
  {
    "name": "Kentucky Science Center",
    "city": "Louisville",
    "state": "KY",
    "category": "Science & Discovery Centers",
    "subcategory": "Science Center"
  },
  {
    "name": "Louisville Zoo",
    "city": "Louisville",
    "state": "KY",
    "category": "Farms, Zoos & Nature Centers",
    "subcategory": "Zoo"
  },
  {
    "name": "Sky Zone Louisville",
    "city": "Louisville",
    "state": "KY",
    "category": "Trampoline & Ninja Parks",
    "subcategory": "Trampoline Park"
  },
  {
    "name": "Urban Air Lexington",
    "city": "Lexington",
    "state": "KY",
    "category": "Trampoline & Ninja Parks",
    "subcategory": "Trampoline Park"
  },
  {
    "name": "Grand Central Station Louisville",
    "city": "Louisville",
    "state": "KY",
    "category": "Indoor Playgrounds",
    "subcategory": "Indoor Play"
  },
  {
    "name": "Iceland Sports Complex",
    "city": "Louisville",
    "state": "KY",
    "category": "Ice Skating Rinks",
    "subcategory": "Ice Skating"
  },
  {
    "name": "Lexington Ice Center",
    "city": "Lexington",
    "state": "KY",
    "category": "Ice Skating Rinks",
    "subcategory": "Ice Skating"
  },
  {
    "name": "Louisville Gymnastics Academy",
    "city": "Louisville",
    "state": "KY",
    "category": "Gymnastics Centers",
    "subcategory": "Gymnastics"
  },
  {
    "name": "Kentucky Kingdom",
    "city": "Louisville",
    "state": "KY",
    "category": "Swimming & Splash Pads",
    "subcategory": "Water Park"
  },
  {
    "name": "Adventure Falls Mini Golf",
    "city": "Richmond",
    "state": "KY",
    "category": "Mini Golf & Batting Cages",
    "subcategory": "Mini Golf"
  },
  {
    "name": "Painting with a Twist Louisville",
    "city": "Louisville",
    "state": "KY",
    "category": "Art Studios & Pottery",
    "subcategory": "Art Studio"
  },
  {
    "name": "Lexington Ice Center",
    "city": "Lexington",
    "state": "KY",
    "category": "Ice Skating Rinks",
    "subcategory": "Ice Rink"
  },
  {
    "name": "Bowlero Louisville",
    "city": "Louisville",
    "state": "KY",
    "category": "Bowling Alleys",
    "subcategory": "Bowling Alley"
  },
  {
    "name": "Mega Cavern Louisville",
    "city": "Louisville",
    "state": "KY",
    "category": "Science & Discovery Centers",
    "subcategory": "Science Museum"
  },
  {
    "name": "Louisville Slugger Museum",
    "city": "Louisville",
    "state": "KY",
    "category": "Science & Discovery Centers",
    "subcategory": "Museum"
  },
  {
    "name": "COSI",
    "city": "Columbus",
    "state": "OH",
    "category": "Science & Discovery Centers",
    "subcategory": "Science Center"
  },
  {
    "name": "Cincinnati Zoo",
    "city": "Cincinnati",
    "state": "OH",
    "category": "Farms, Zoos & Nature Centers",
    "subcategory": "Zoo"
  },
  {
    "name": "Columbus Zoo",
    "city": "Columbus",
    "state": "OH",
    "category": "Farms, Zoos & Nature Centers",
    "subcategory": "Zoo"
  },
  {
    "name": "Sky Zone Columbus",
    "city": "Columbus",
    "state": "OH",
    "category": "Trampoline & Ninja Parks",
    "subcategory": "Trampoline Park"
  },
  {
    "name": "Urban Air Cincinnati",
    "city": "Cincinnati",
    "state": "OH",
    "category": "Trampoline & Ninja Parks",
    "subcategory": "Trampoline Park"
  },
  {
    "name": "Altitude Trampoline Cleveland",
    "city": "Cleveland",
    "state": "OH",
    "category": "Trampoline & Ninja Parks",
    "subcategory": "Trampoline Park"
  },
  {
    "name": "Grand Central Station Columbus",
    "city": "Columbus",
    "state": "OH",
    "category": "Indoor Playgrounds",
    "subcategory": "Indoor Play"
  },
  {
    "name": "Children's Museum of Indianapolis",
    "city": "Indianapolis",
    "state": "IN",
    "category": "Children's Museums",
    "subcategory": "Interactive Museum"
  },
  {
    "name": "Indianapolis Zoo",
    "city": "Indianapolis",
    "state": "IN",
    "category": "Farms, Zoos & Nature Centers",
    "subcategory": "Zoo"
  },
  {
    "name": "Sky Zone Indianapolis",
    "city": "Indianapolis",
    "state": "IN",
    "category": "Trampoline & Ninja Parks",
    "subcategory": "Trampoline Park"
  },
  {
    "name": "Urban Air Fort Wayne",
    "city": "Fort Wayne",
    "state": "IN",
    "category": "Trampoline & Ninja Parks",
    "subcategory": "Trampoline Park"
  },
  {
    "name": "Grand Central Station Indianapolis",
    "city": "Indianapolis",
    "state": "IN",
    "category": "Indoor Playgrounds",
    "subcategory": "Indoor Play"
  },
  {
    "name": "Michigan Science Center",
    "city": "Detroit",
    "state": "MI",
    "category": "Science & Discovery Centers",
    "subcategory": "Science Center"
  },
  {
    "name": "Detroit Zoo",
    "city": "Detroit",
    "state": "MI",
    "category": "Farms, Zoos & Nature Centers",
    "subcategory": "Zoo"
  },
  {
    "name": "Sky Zone Detroit",
    "city": "Detroit",
    "state": "MI",
    "category": "Trampoline & Ninja Parks",
    "subcategory": "Trampoline Park"
  },
  {
    "name": "Urban Air Grand Rapids",
    "city": "Grand Rapids",
    "state": "MI",
    "category": "Trampoline & Ninja Parks",
    "subcategory": "Trampoline Park"
  },
  {
    "name": "Grand Central Station Detroit",
    "city": "Detroit",
    "state": "MI",
    "category": "Indoor Playgrounds",
    "subcategory": "Indoor Play"
  },
  {
    "name": "Chicago Children's Museum",
    "city": "Chicago",
    "state": "IL",
    "category": "Children's Museums",
    "subcategory": "Interactive Museum"
  },
  {
    "name": "Museum of Science and Industry",
    "city": "Chicago",
    "state": "IL",
    "category": "Science & Discovery Centers",
    "subcategory": "Science Museum"
  },
  {
    "name": "Shedd Aquarium Chicago",
    "city": "Chicago",
    "state": "IL",
    "category": "Science & Discovery Centers",
    "subcategory": "Aquarium"
  },
  {
    "name": "Lincoln Park Zoo",
    "city": "Chicago",
    "state": "IL",
    "category": "Farms, Zoos & Nature Centers",
    "subcategory": "Zoo"
  },
  {
    "name": "Sky Zone Chicago",
    "city": "Chicago",
    "state": "IL",
    "category": "Trampoline & Ninja Parks",
    "subcategory": "Trampoline Park"
  },
  {
    "name": "Urban Air Aurora",
    "city": "Aurora",
    "state": "IL",
    "category": "Trampoline & Ninja Parks",
    "subcategory": "Trampoline Park"
  },
  {
    "name": "Altitude Trampoline Springfield",
    "city": "Springfield",
    "state": "IL",
    "category": "Trampoline & Ninja Parks",
    "subcategory": "Trampoline Park"
  },
  {
    "name": "Grand Central Station Chicago",
    "city": "Chicago",
    "state": "IL",
    "category": "Indoor Playgrounds",
    "subcategory": "Indoor Play"
  },
  {
    "name": "Madison Children's Museum",
    "city": "Madison",
    "state": "WI",
    "category": "Children's Museums",
    "subcategory": "Interactive Museum"
  },
  {
    "name": "Henry Vilas Zoo",
    "city": "Madison",
    "state": "WI",
    "category": "Farms, Zoos & Nature Centers",
    "subcategory": "Zoo"
  },
  {
    "name": "Milwaukee County Zoo",
    "city": "Milwaukee",
    "state": "WI",
    "category": "Farms, Zoos & Nature Centers",
    "subcategory": "Zoo"
  },
  {
    "name": "Sky Zone Madison",
    "city": "Madison",
    "state": "WI",
    "category": "Trampoline & Ninja Parks",
    "subcategory": "Trampoline Park"
  },
  {
    "name": "Urban Air Milwaukee",
    "city": "Milwaukee",
    "state": "WI",
    "category": "Trampoline & Ninja Parks",
    "subcategory": "Trampoline Park"
  },
  {
    "name": "Grand Central Station Madison",
    "city": "Madison",
    "state": "WI",
    "category": "Indoor Playgrounds",
    "subcategory": "Indoor Play"
  },
  {
    "name": "West Virginia Children's Museum",
    "city": "Charleston",
    "state": "WV",
    "category": "Children's Museums",
    "subcategory": "Interactive Museum"
  },
  {
    "name": "Oglebay's Good Zoo",
    "city": "Wheeling",
    "state": "WV",
    "category": "Farms, Zoos & Nature Centers",
    "subcategory": "Zoo"
  },
  {
    "name": "Sky Zone Charleston",
    "city": "Charleston",
    "state": "WV",
    "category": "Trampoline & Ninja Parks",
    "subcategory": "Trampoline Park"
  },
  {
    "name": "Urban Air Huntington",
    "city": "Huntington",
    "state": "WV",
    "category": "Trampoline & Ninja Parks",
    "subcategory": "Trampoline Park"
  },
  {
    "name": "VT Children's Museum",
    "city": "Bennington",
    "state": "VT",
    "category": "Children's Museums",
    "subcategory": "Interactive Museum"
  },
  {
    "name": "Vermont Zoo",
    "city": "Waterbury",
    "state": "VT",
    "category": "Farms, Zoos & Nature Centers",
    "subcategory": "Nature Center"
  },
  {
    "name": "Sky Zone Montpelier",
    "city": "Montpelier",
    "state": "VT",
    "category": "Trampoline & Ninja Parks",
    "subcategory": "Trampoline Park"
  },
  {
    "name": "Montshire Museum of Science",
    "city": "Norwich",
    "state": "VT",
    "category": "Science & Discovery Centers",
    "subcategory": "Science Museum"
  },
  {
    "name": "Cairns Arena",
    "city": "South Burlington",
    "state": "VT",
    "category": "Ice Skating Rinks",
    "subcategory": "Ice Arena"
  },
  {
    "name": "Spare Time Entertainment",
    "city": "Colchester",
    "state": "VT",
    "category": "Bowling Alleys",
    "subcategory": "Bowling"
  },
  {
    "name": "MetroRock Vermont",
    "city": "Winooski",
    "state": "VT",
    "category": "Climbing Gyms",
    "subcategory": "Indoor Climbing"
  },
  {
    "name": "ECHO, Leahy Center for Lake Champlain",
    "city": "Burlington",
    "state": "VT",
    "category": "Science & Discovery Centers",
    "subcategory": "Science Museum"
  },
  {
    "name": "Fairbanks Museum & Planetarium",
    "city": "Saint Johnsbury",
    "state": "VT",
    "category": "Science & Discovery Centers",
    "subcategory": "Science Museum"
  },
  {
    "name": "Leddy Park Arena",
    "city": "Burlington",
    "state": "VT",
    "category": "Ice Skating Rinks",
    "subcategory": "Ice Rink"
  },
  {
    "name": "Shelburne Museum",
    "city": "Shelburne",
    "state": "VT",
    "category": "Farms, Zoos & Nature Centers",
    "subcategory": "Museum"
  },
  {
    "name": "Billings Farm and Museum",
    "city": "Woodstock",
    "state": "VT",
    "category": "Farms, Zoos & Nature Centers",
    "subcategory": "Farm"
  },
  {
    "name": "Maine Discovery Museum",
    "city": "Bangor",
    "state": "ME",
    "category": "Science & Discovery Centers",
    "subcategory": "Children's Discovery Museum"
  },
  {
    "name": "Family Ice Center",
    "city": "Falmouth",
    "state": "ME",
    "category": "Ice Skating Rinks",
    "subcategory": "Ice Arena"
  },
  {
    "name": "EVO Rock & Fitness",
    "city": "Portland",
    "state": "ME",
    "category": "Climbing Gyms",
    "subcategory": "Indoor Climbing"
  },
  {
    "name": "Spare Time Entertainment",
    "city": "Portland",
    "state": "ME",
    "category": "Bowling Alleys",
    "subcategory": "Bowling"
  },
  {
    "name": "Happy Wheels Skate Center",
    "city": "Westbrook",
    "state": "ME",
    "category": "Roller Skating Rinks",
    "subcategory": "Roller Skating"
  },
  {
    "name": "Children's Museum & Theatre of Maine",
    "city": "Portland",
    "state": "ME",
    "category": "Children's Museums",
    "subcategory": "Children's Museum"
  },
  {
    "name": "Maine Wildlife Park",
    "city": "Gray",
    "state": "ME",
    "category": "Farms, Zoos & Nature Centers",
    "subcategory": "Wildlife Park"
  },
  {
    "name": "Portland Observatory",
    "city": "Portland",
    "state": "ME",
    "category": "Science & Discovery Centers",
    "subcategory": "Science Museum"
  },
  {
    "name": "Funtown Splashtown USA",
    "city": "Saco",
    "state": "ME",
    "category": "Swimming & Splash Pads",
    "subcategory": "Water Park"
  },
  {
    "name": "Big Air Trampoline Park",
    "city": "Portland",
    "state": "ME",
    "category": "Trampoline & Ninja Parks",
    "subcategory": "Trampoline Park"
  },
  {
    "name": "Conway Arena",
    "city": "Nashua",
    "state": "NH",
    "category": "Ice Skating Rinks",
    "subcategory": "Ice Arena"
  },
  {
    "name": "Lakeside Lanes",
    "city": "Manchester",
    "state": "NH",
    "category": "Bowling Alleys",
    "subcategory": "Candlepin Bowling"
  },
  {
    "name": "Leda Lanes",
    "city": "Nashua",
    "state": "NH",
    "category": "Bowling Alleys",
    "subcategory": "Candlepin Bowling"
  },
  {
    "name": "Funspot Family Fun Center",
    "city": "Laconia",
    "state": "NH",
    "category": "Family Entertainment Centers",
    "subcategory": "Arcade & Bowling"
  },
  {
    "name": "SEE Science Center",
    "city": "Manchester",
    "state": "NH",
    "category": "Science & Discovery Centers",
    "subcategory": "Science Museum"
  },
  {
    "name": "Children's Museum of New Hampshire",
    "city": "Dover",
    "state": "NH",
    "category": "Children's Museums",
    "subcategory": "Children's Museum"
  },
  {
    "name": "McAuliffe-Shepard Discovery Center",
    "city": "Concord",
    "state": "NH",
    "category": "Science & Discovery Centers",
    "subcategory": "Science Museum"
  },
  {
    "name": "Urban Air Manchester",
    "city": "Manchester",
    "state": "NH",
    "category": "Trampoline & Ninja Parks",
    "subcategory": "Trampoline Park"
  },
  {
    "name": "Canobie Lake Park",
    "city": "Salem",
    "state": "NH",
    "category": "Family Entertainment Centers",
    "subcategory": "Amusement Park"
  },
  {
    "name": "Story Land",
    "city": "Glen",
    "state": "NH",
    "category": "Family Entertainment Centers",
    "subcategory": "Theme Park"
  },
  {
    "name": "South Charleston Memorial Ice Arena",
    "city": "South Charleston",
    "state": "WV",
    "category": "Ice Skating Rinks",
    "subcategory": "Ice Arena"
  },
  {
    "name": "Mylan Park Ice Pavilion",
    "city": "Morgantown",
    "state": "WV",
    "category": "Ice Skating Rinks",
    "subcategory": "Ice Arena"
  },
  {
    "name": "Roll-A-Rama Roller Rink",
    "city": "Huntington",
    "state": "WV",
    "category": "Roller Skating Rinks",
    "subcategory": "Roller Skating"
  },
  {
    "name": "Suburban Lanes",
    "city": "Morgantown",
    "state": "WV",
    "category": "Bowling Alleys",
    "subcategory": "Bowling"
  },
  {
    "name": "Clay Center for the Arts & Sciences",
    "city": "Charleston",
    "state": "WV",
    "category": "Science & Discovery Centers",
    "subcategory": "Science Museum"
  },
  {
    "name": "Good Zoo at Oglebay Resort",
    "city": "Wheeling",
    "state": "WV",
    "category": "Farms, Zoos & Nature Centers",
    "subcategory": "Zoo"
  },
  {
    "name": "Oglebay Resort Ice Arena",
    "city": "Wheeling",
    "state": "WV",
    "category": "Ice Skating Rinks",
    "subcategory": "Ice Rink"
  },
  {
    "name": "Sky Zone Charleston",
    "city": "Charleston",
    "state": "WV",
    "category": "Trampoline & Ninja Parks",
    "subcategory": "Trampoline Park"
  },
  {
    "name": "Launch Pad Trampoline Park",
    "city": "Morgantown",
    "state": "WV",
    "category": "Trampoline & Ninja Parks",
    "subcategory": "Trampoline Park"
  },
  {
    "name": "Morgantown Municipal Ice Arena",
    "city": "Morgantown",
    "state": "WV",
    "category": "Ice Skating Rinks",
    "subcategory": "Ice Rink"
  },
  {
    "name": "Suburban Lanes",
    "city": "Morgantown",
    "state": "WV",
    "category": "Bowling Alleys",
    "subcategory": "Bowling Alley"
  },
  {
    "name": "Billy Bob's Wonderland",
    "city": "Huntington",
    "state": "WV",
    "category": "Family Entertainment Centers",
    "subcategory": "FEC"
  },
  {
    "name": "Outside-In Climbing Gym",
    "city": "Beckley",
    "state": "WV",
    "category": "Climbing Gyms",
    "subcategory": "Rock Climbing"
  },
  {
    "name": "Coonskin Park",
    "city": "Charleston",
    "state": "WV",
    "category": "Farms, Zoos & Nature Centers",
    "subcategory": "Park"
  },
  {
    "name": "Lynn Meadows Discovery Center",
    "city": "Gulfport",
    "state": "MS",
    "category": "Children's Museums",
    "subcategory": "Interactive Museum"
  },
  {
    "name": "Mississippi Coast Coliseum",
    "city": "Biloxi",
    "state": "MS",
    "category": "Ice Skating Rinks",
    "subcategory": "Seasonal Ice Skating"
  },
  {
    "name": "Funtime Skateland",
    "city": "Pearl",
    "state": "MS",
    "category": "Roller Skating Rinks",
    "subcategory": "Roller Skating"
  },
  {
    "name": "Fannin Lanes",
    "city": "Brandon",
    "state": "MS",
    "category": "Bowling Alleys",
    "subcategory": "Bowling"
  },
  {
    "name": "Mississippi Museum of Natural Science",
    "city": "Jackson",
    "state": "MS",
    "category": "Science & Discovery Centers",
    "subcategory": "Science Museum"
  },
  {
    "name": "Children's Museum of Mississippi",
    "city": "Jackson",
    "state": "MS",
    "category": "Children's Museums",
    "subcategory": "Children's Museum"
  },
  {
    "name": "Mississippi Aquarium",
    "city": "Gulfport",
    "state": "MS",
    "category": "Science & Discovery Centers",
    "subcategory": "Aquarium"
  },
  {
    "name": "Sky Zone Jackson",
    "city": "Jackson",
    "state": "MS",
    "category": "Trampoline & Ninja Parks",
    "subcategory": "Trampoline Park"
  },
  {
    "name": "Hattiesburg Zoo",
    "city": "Hattiesburg",
    "state": "MS",
    "category": "Farms, Zoos & Nature Centers",
    "subcategory": "Zoo"
  }
]